nsxez/__init__.py
nsxez/operations.py
nsxez-1.0.dist-info/LICENSE
nsxez-1.0.dist-info/METADATA
nsxez-1.0.dist-info/WHEEL
nsxez-1.0.dist-info/top_level.txt
nsxez-1.0.dist-info/RECORD
